.gitignore
LICENSE
README.md
dev-requirements.txt
setup.py
py_db_wrapper/__init__.py
py_db_wrapper/connection.py
py_db_wrapper/dialect.py
py_db_wrapper/exceptions.py
py_db_wrapper/sqlType.py
py_db_wrapper/utils.py
py_db_wrapper.egg-info/PKG-INFO
py_db_wrapper.egg-info/SOURCES.txt
py_db_wrapper.egg-info/dependency_links.txt
py_db_wrapper.egg-info/requires.txt
py_db_wrapper.egg-info/top_level.txt
py_db_wrapper/sql/__init__.py
py_db_wrapper/sql/statement.py
tests/__init__.py
tests/test.py
tests/test_connection.py
tests/test_dialect.py
tests/test_sqltype.py
tests/test_statement.py